jigsawwm/__init__.py
jigsawwm/objectcache.py
jigsawwm/worker.py
jigsawwm/app/__init__.py
jigsawwm/app/browser.py
jigsawwm/app/daemon.py
jigsawwm/app/job.py
jigsawwm/app/services.py
jigsawwm/app/smartstart.py
jigsawwm/app/state.py
jigsawwm/app/tasks.py
jigsawwm/assets/dark.css
jigsawwm/assets/dwindle.png
jigsawwm/assets/icons.svg
jigsawwm/assets/logo.png
jigsawwm/assets/obs.png
jigsawwm/assets/wide-dwindle.png
jigsawwm/jmk/__init__.py
jigsawwm/jmk/combo.py
jigsawwm/jmk/core.py
jigsawwm/jmk/hotkey.py
jigsawwm/jmk/jmk_service.py
jigsawwm/jmk/sysinout.py
jigsawwm/tiler/__init__.py
jigsawwm/tiler/layouts.py
jigsawwm/tiler/tilers.py
jigsawwm/ui/__init__.py
jigsawwm/ui/app.py
jigsawwm/ui/dialog.py
jigsawwm/ui/splash.py
jigsawwm/w32/__init__.py
jigsawwm/w32/hook.py
jigsawwm/w32/monitor.py
jigsawwm/w32/monitor_detector.py
jigsawwm/w32/powerprofile.py
jigsawwm/w32/process.py
jigsawwm/w32/reg.py
jigsawwm/w32/sendinput.py
jigsawwm/w32/util_hook_input.py
jigsawwm/w32/virtdesk.py
jigsawwm/w32/vk.py
jigsawwm/w32/window.py
jigsawwm/w32/window_detector.py
jigsawwm/w32/window_structs.py
jigsawwm/w32/winevent.py
jigsawwm/wm/__init__.py
jigsawwm/wm/config.py
jigsawwm/wm/const.py
jigsawwm/wm/debug_state.py
jigsawwm/wm/manager.py
jigsawwm/wm/monitor_state.py
jigsawwm/wm/theme.py
jigsawwm/wm/virtdesk_state.py
jigsawwm/wm/wm_service.py
jigsawwm/wm/workspace_state.py
jigsawwm-3.0.1.dist-info/licenses/LICENSE
jigsawwm-3.0.1.dist-info/METADATA
jigsawwm-3.0.1.dist-info/WHEEL
jigsawwm-3.0.1.dist-info/top_level.txt
jigsawwm-3.0.1.dist-info/RECORD
