Metadata-Version: 2.4
Name: jigsawwm
Version: 3.0.1
Summary: JigsawWM is a free and open-source project that aims to increase your productivity by offering a set of automation facilities, including the jmk module as an AHK alternative, a Tiling Window Manager to free you from managing windows manually and the Daemon to support any customization you may have in mind.
Author-email: Klesh Wong <klesh@qq.com>
Project-URL: Documentation, https://jigsawwm.readthedocs.io/en/latest/
Project-URL: Source Code, https://github.com/klesh/JigsawWM
Project-URL: Issue Tracker, https://github.com/klesh/JigsawWM/issues
Classifier: License :: OSI Approved :: GNU Lesser General Public License v3 (LGPLv3)
Classifier: Operating System :: Microsoft :: Windows
Classifier: Operating System :: POSIX :: Linux
Classifier: Operating System :: Unix
Classifier: Operating System :: MacOS
Classifier: Operating System :: POSIX :: BSD
Requires-Python: >=3.8
License-File: LICENSE
Requires-Dist: pyside6~=6.8.1
Requires-Dist: mailcalaid~=1.0.2
Requires-Dist: pyvda~=0.4.3
Dynamic: license-file
